multipletau_cor_tttr/CCF.so
multipletau_cor_tttr/__init__.py
multipletau_cor_tttr/correlate.py
multipletau_cor_tttr/example.py
multipletau_cor_tttr/sample_data.npy
multipletau_cor_tttr-0.1.4.dist-info/LICENSE
multipletau_cor_tttr-0.1.4.dist-info/METADATA
multipletau_cor_tttr-0.1.4.dist-info/WHEEL
multipletau_cor_tttr-0.1.4.dist-info/top_level.txt
multipletau_cor_tttr-0.1.4.dist-info/RECORD
