Metadata-Version: 2.1
Name: multipletau-cor-tttr
Version: 0.1.4
Summary: Library for correlation of time-tagged time-resolved photon data for fluorescence correlation spectroscopy (FCS) analysis.
Home-page: http://testpypi.python.org/pypi/multipletau_cor_tttr/
Author: Anders Barth
Author-email: anders.barth@gmail.com
License: MIT
Keywords: FCS Fluorescence Correlation Spectroscopy Single Photon Counting TTTR Multiple-tau algorithm
Platform: UNKNOWN
Classifier: Programming Language :: Python :: 3
Classifier: License :: OSI Approved :: MIT License
Classifier: Operating System :: OS Independent
Requires-Dist: numpy
Requires-Dist: matplotlib
